eazyprofiler/GetStats.py
eazyprofiler/__init__.py
eazyprofiler/__main__.py
eazyprofiler/_version.py
eazyprofiler/cli.py
eazyprofiler-0.1.3.dist-info/LICENSE
eazyprofiler-0.1.3.dist-info/METADATA
eazyprofiler-0.1.3.dist-info/WHEEL
eazyprofiler-0.1.3.dist-info/entry_points.txt
eazyprofiler-0.1.3.dist-info/top_level.txt
eazyprofiler-0.1.3.dist-info/RECORD
